lycium_rest/__init__.py
lycium_rest/migrationutils.py
lycium_rest/formvalidation/__init__.py
lycium_rest/formvalidation/formitemprops.py
lycium_rest/formvalidation/formutils.py
lycium_rest/formvalidation/modifyingbeheviorform.py
lycium_rest/formvalidation/modifyingbeheviorformfields.py
lycium_rest/formvalidation/validators.py
lycium_rest/locales/basic.en_US.yml
lycium_rest/locales/basic.zh_CN.yml
lycium_rest/model/__init__.py
lycium_rest/model/supports/__init__.py
lycium_rest/model/supports/migration.py
lycium_rest/model/supports/migration_progress.py
lycium_rest/restfulwrapper/__init__.py
lycium_rest/restfulwrapper/modelapihandlers.py
lycium_rest/restfulwrapper/modelrelationhandlers.py
lycium_rest/restfulwrapper/pagedescriptorhandlers.py
lycium_rest/restfulwrapper/register.py
lycium_rest/restfulwrapper/restdescriptor.py
lycium_rest/restfulwrapper/utils.py
lycium_rest/restfulwrapper/accesscontrol/__init__.py
lycium_rest/restfulwrapper/accesscontrol/authorizedsession.py
lycium_rest/utilities/__init__.py
lycium_rest/utilities/treedata.py
lycium_rest/valueobjects/__init__.py
lycium_rest/valueobjects/responseobject.py
lycium_rest/valueobjects/resultcodes.py
lycium_rest-0.0.4.dist-info/LICENSE
lycium_rest-0.0.4.dist-info/METADATA
lycium_rest-0.0.4.dist-info/WHEEL
lycium_rest-0.0.4.dist-info/top_level.txt
lycium_rest-0.0.4.dist-info/RECORD
