Metadata-Version: 2.1
Name: lycium-rest
Version: 0.0.4
Summary: common python programing encapsulation library
Home-page: https://github.com/libpub/lycium-rest
Author: kevinyjn
Author-email: kevinyjn@gmail.com
Classifier: Programming Language :: Python :: 3
Classifier: License :: OSI Approved :: MIT License
Classifier: Operating System :: OS Independent
Requires-Python: >=3.6
License-File: LICENSE
Requires-Dist: pycrypto
Requires-Dist: sqlalchemy (==1.4.25)
Requires-Dist: IPy
Requires-Dist: requests
Requires-Dist: tornado
Requires-Dist: hawthorn
Requires-Dist: PyJWT
Requires-Dist: python-i18n[yaml]
